QiAlgo_OCR/Qi.py
QiAlgo_OCR/__init__.py
QiAlgo_OCR/model/model.onnx
QiAlgo_OCR-1.0.1.dist-info/LICENSE
QiAlgo_OCR-1.0.1.dist-info/METADATA
QiAlgo_OCR-1.0.1.dist-info/WHEEL
QiAlgo_OCR-1.0.1.dist-info/top_level.txt
QiAlgo_OCR-1.0.1.dist-info/RECORD
