Metadata-Version: 2.1
Name: QiAlgo-OCR
Version: 1.0.1
Summary: QiAlgo_OCR(青祁OCR)是基于'QiAlgoML青祁机器学习项目'中的神经网络子项目分离开发的Python库，是一种对特定场景进行光学字符识别（Optical Character Recognition，简称OCR）的解决方案。
Home-page: https://github.com/Morton-L/QiAlgo_OCR
Author: Morton Li
Author-email: Morton Li <Morton.L@Outlook.com>
Project-URL: Homepage, https://github.com/Morton-L/QiAlgo_OCRt
Project-URL: Bug Tracker, https://github.com/Morton-L/QiAlgo_OCR/issues
Classifier: Programming Language :: Python :: 3.11
Classifier: License :: OSI Approved :: MIT License
Requires-Python: >=3.11
License-File: LICENSE
Requires-Dist: onnxruntime (~=1.16.1)
Requires-Dist: Pillow (~=10.0.1)
Requires-Dist: torch (==2.1.0)
Requires-Dist: torchvision (==0.16.0)
Requires-Dist: PyYAML (~=6.0.1)
